pylabml/__init__.py
pylabml/label.py
pylabml/labeller.py
pylabml-0.1.0.dist-info/WHEEL
pylabml-0.1.0.dist-info/METADATA
pylabml-0.1.0.dist-info/RECORD
